Workbook
Name Slicer_Category: #N/A
Name Slicer_Month_Name: #N/A

Sheet Sales_Raw
A1: Sale_ID | B1: Date | C1: Week_Number | D1: Month | E1: Month_Name | F1: Product_ID | G1: Category | H1: Units_Sold | I1: Sale_Price | J1: Discount_%
A2: S0002 | B2: 2024-01-01 | C2: 1 | D2: 1 | E2: January | F2: P006 | G2: Topwear | H2: 5 | I2: 408 | J2: 15
A3: S0134 | B3: 2024-01-01 | C3: 1 | D3: 1 | E3: January | F3: P026 | G3: Winter Collection | H3: 1 | I3: 468 | J3: 10
A4: S0096 | B4: 2024-01-01 | C4: 1 | D4: 1 | E4: January | F4: P012 | G4: Footwear | H4: 4 | I4: 1377 | J4: 15
A5: S0137 | B5: 2024-01-01 | C5: 1 | D5: 1 | E5: January | F5: P010 | G5: Bottomwear | H5: 5 | I5: 500 | J5: 0
A6: S0010 | B6: 2024-01-01 | C6: 1 | D6: 1 | E6: January | F6: P021 | G6: Accessories | H6: 2 | I6: 1000 | J6: 0
A7: S0013 | B7: 2024-01-01 | C7: 1 | D7: 1 | E7: January | F7: P020 | G7: Accessories | H7: 2 | I7: 1350 | J7: 10
A8: S0139 | B8: 2024-01-02 | C8: 1 | D8: 1 | E8: January | F8: P011 | G8: Bottomwear | H8: 2 | I8: 1400 | J8: 0
A9: S0038 | B9: 2024-01-02 | C9: 1 | D9: 1 | E9: January | F9: P010 | G9: Bottomwear | H9: 5 | I9: 425 | J9: 15
A10: S0040 | B10: 2024-01-03 | C10: 1 | D10: 1 | E10: January | F10: P023 | G10: Winter Collection | H10: 4 | I10: 3150 | J10: 0
A11: S0115 | B11: 2024-01-03 | C11: 1 | D11: 1 | E11: January | F11: P016 | G11: Footwear | H11: 3 | I11: 1989 | J11: 15
A12: S0033 | B12: 2024-01-03 | C12: 1 | D12: 1 | E12: January | F12: P002 | G12: Topwear | H12: 5 | I12: 792 | J12: 10
A13: S0062 | B13: 2024-01-03 | C13: 1 | D13: 1 | E13: January | F13: P010 | G13: Bottomwear | H13: 5 | I13: 500 | J13: 0
... A1501: S1397 | B1501: 2024-12-31 | C1501: 1 | D1501: 12 | E1501: December | F1501: P008 | G1501: Bottomwear | H1501: 1 | I1501: 1000 | J1501: 0

Sheet Product_Master
A1: Product_ID | B1: Product_Name | C1: Category | D1: COGS | E1: Launch_Date | F1: Sale_Price
A2: P001 | B2: Classic Cotton Kurta | C2: Topwear | D2: 350 | E2: 2024-01-01 | F2: 770
A3: P002 | B3: Slim Fit Shirt | C3: Topwear | D3: 400 | E3: 2024-01-01 | F3: 880
A4: P003 | B4: Casual T-Shirt | C4: Topwear | D4: 180 | E4: 2024-01-01 | F4: 400
A5: P004 | B5: Formal Blazer | C5: Topwear | D5: 1200 | E5: 2024-01-01 | F5: 2640
A6: P005 | B6: Ethnic Sherwani | C6: Topwear | D6: 2000 | E6: 2024-01-01 | F6: 4400
A7: P006 | B7: Polo Neck Tee | C7: Topwear | D7: 220 | E7: 2024-02-01 | F7: 480
A8: P007 | B8: Slim Fit Jeans | C8: Bottomwear | D8: 600 | E8: 2024-01-01 | F8: 1200
A9: P008 | B9: Chino Trousers | C9: Bottomwear | D9: 500 | E9: 2024-01-01 | F9: 1000
A10: P009 | B10: Ethnic Pyjama | C10: Bottomwear | D10: 300 | E10: 2024-01-01 | F10: 600
A11: P010 | B11: Track Pants | C11: Bottomwear | D11: 250 | E11: 2024-01-01 | F11: 500
A12: P011 | B12: Formal Trousers | C12: Bottomwear | D12: 700 | E12: 2024-01-01 | F12: 1400
A13: P012 | B13: Leather Loafers | C13: Footwear | D13: 900 | E13: 2024-01-01 | F13: 1620
... A31: P030 | B31: Breathable Joggers | C31: Summer Collection | D31: 350 | E31: 2024-04-01 | F31: 700

Sheet Budget_Plan
A1: Month | B1: Month_Name | C1: Category | D1: Budgeted_Revenue_INR | E1: Budgeted_Units
A2: 1 | B2: January | C2: Topwear | D2: 67200 | E2: 64
A3: 1 | B3: January | C3: Bottomwear | D3: 94100 | E3: 109
A4: 1 | B4: January | C4: Footwear | D4: 86700 | E4: 73
A5: 1 | B5: January | C5: Accessories | D5: 98700 | E5: 77
A6: 1 | B6: January | C6: Winter Collection | D6: 151600 | E6: 108
A7: 1 | B7: January | C7: Summer Collection | D7: 1000 | E7: 5
A8: 2 | B8: February | C8: Topwear | D8: 63700 | E8: 62
A9: 2 | B9: February | C9: Bottomwear | D9: 38000 | E9: 45
A10: 2 | B10: February | C10: Footwear | D10: 76600 | E10: 47
A11: 2 | B11: February | C11: Accessories | D11: 179500 | E11: 58
A12: 2 | B12: February | C12: Winter Collection | D12: 97100 | E12: 66
A13: 2 | B13: February | C13: Summer Collection | D13: 2500 | E13: 5
... A73: 12 | B73: December | C73: Summer Collection | D73: 1800 | E73: 5

Sheet Returns_Raw
A1: Return_ID | B1: Sale_ID | C1: Date | D1: Product_ID | E1: Category | F1: Units_Returned | G1: Reason
A2: R0001 | B2: S1034 | C2: 2024-10-30 | D2: P004 | E2: Topwear | F2: 2 | G2: Quality Issue
A3: R0002 | B3: S1440 | C3: 2024-12-13 | D3: P023 | E3: Winter Collection | F3: 2 | G3: Changed Mind
A4: R0003 | B4: S0416 | C4: 2024-04-30 | D4: P005 | E4: Topwear | F4: 5 | G4: Wrong Item
A5: R0004 | B5: S0338 | C5: 2024-04-27 | D5: P017 | E5: Accessories | F5: 1 | G5: Damaged Product
A6: R0005 | B6: S0454 | C6: 2024-05-10 | D6: P011 | E6: Bottomwear | F6: 4 | G6: Changed Mind
A7: R0006 | B7: S0793 | C7: 2024-08-30 | D7: P013 | E7: Footwear | F7: 2 | G7: Wrong Item
A8: R0007 | B8: S1012 | C8: 2024-10-16 | D8: P014 | E8: Footwear | F8: 3 | G8: Size Issue
A9: R0008 | B9: S0784 | C9: 2024-07-20 | D9: P027 | E9: Summer Collection | F9: 4 | G9: Wrong Item
A10: R0009 | B10: S1308 | C10: 2024-11-26 | D10: P001 | E10: Topwear | F10: 1 | G10: Quality Issue
A11: R0010 | B11: S0330 | C11: 2024-03-19 | D11: P017 | E11: Accessories | F11: 2 | G11: Damaged Product
A12: R0011 | B12: S0986 | C12: 2024-09-07 | D12: P012 | E12: Footwear | F12: 1 | G12: Size Issue
A13: R0012 | B13: S1437 | C13: 2024-12-27 | D13: P002 | E13: Topwear | F13: 3 | G13: Damaged Product
... A105: R0104 | B105: S0487 | C105: 2024-05-15 | D105: P007 | E105: Bottomwear | F105: 2 | G105: Quality Issue

Sheet Sales_Master
A1: Sale_ID | B1: Date | C1: Week_Number | D1: Month | E1: Month_Name | F1: Product_ID | G1: Category | H1: Units_Sold | I1: Sale_Price | J1: Discount_% | K1: Product_Name | L1: COGS | M1: Revenue_INR | N1: Total_COGS | O1: Gross_Profit | P1: Gross_Margin_% | Q1: Units_Returned | R1: Units_Returned_Clean | S1: Net_Units_Sold | T1: Net_Revenue_INR
A2: S0002 | B2: 45292 | C2: 1 | D2: 1 | E2: January | F2: P006 | G2: Topwear | H2: 5 | I2: 408 | J2: 15 | K2: Polo Neck Tee | L2: 220 | M2: 2040 | N2: 1100 | O2: 940 | P2: 0.46078431 | Q2: 0 | R2: 0 | S2: 5 | T2: 2040
A3: S0119 | B3: 45296 | C3: 1 | D3: 1 | E3: January | F3: P006 | G3: Topwear | H3: 3 | I3: 408 | J3: 15 | K3: Polo Neck Tee | L3: 220 | M3: 1224 | N3: 660 | O3: 564 | P3: 0.46078431 | Q3: 0 | R3: 0 | S3: 3 | T3: 1224
A4: S0134 | B4: 45292 | C4: 1 | D4: 1 | E4: January | F4: P026 | G4: Winter Collection | H4: 1 | I4: 468 | J4: 10 | K4: Woolen Muffler | L4: 250 | M4: 468 | N4: 250 | O4: 218 | P4: 0.46581197 | Q4: 0 | R4: 0 | S4: 1 | T4: 468
A5: S0110 | B5: 45295 | C5: 1 | D5: 1 | E5: January | F5: P026 | G5: Winter Collection | H5: 4 | I5: 520 | J5: 0 | K5: Woolen Muffler | L5: 250 | M5: 2080 | N5: 1000 | O5: 1080 | P5: 0.51923077 | Q5: 0 | R5: 0 | S5: 4 | T5: 2080
A6: S0033 | B6: 45294 | C6: 1 | D6: 1 | E6: January | F6: P002 | G6: Topwear | H6: 5 | I6: 792 | J6: 10 | K6: Slim Fit Shirt | L6: 400 | M6: 3960 | N6: 2000 | O6: 1960 | P6: 0.49494949 | Q6: 0 | R6: 0 | S6: 5 | T6: 3960
A7: S0014 | B7: 45298 | C7: 1 | D7: 1 | E7: January | F7: P002 | G7: Topwear | H7: 4 | I7: 748 | J7: 15 | K7: Slim Fit Shirt | L7: 400 | M7: 2992 | N7: 1600 | O7: 1392 | P7: 0.46524064 | Q7: 0 | R7: 0 | S7: 4 | T7: 2992
A8: S0096 | B8: 45292 | C8: 1 | D8: 1 | E8: January | F8: P012 | G8: Footwear | H8: 4 | I8: 1377 | J8: 15 | K8: Leather Loafers | L8: 900 | M8: 5508 | N8: 3600 | O8: 1908 | P8: 0.34640523 | Q8: 0 | R8: 0 | S8: 4 | T8: 5508
A9: S0083 | B9: 45294 | C9: 1 | D9: 1 | E9: January | F9: P012 | G9: Footwear | H9: 1 | I9: 1539 | J9: 5 | K9: Leather Loafers | L9: 900 | M9: 1539 | N9: 900 | O9: 639 | P9: 0.41520468 | Q9: 0 | R9: 0 | S9: 1 | T9: 1539
A10: S0137 | B10: 45292 | C10: 1 | D10: 1 | E10: January | F10: P010 | G10: Bottomwear | H10: 5 | I10: 500 | J10: 0 | K10: Track Pants | L10: 250 | M10: 2500 | N10: 1250 | O10: 1250 | P10: 0.5 | Q10: 0 | R10: 0 | S10: 5 | T10: 2500
A11: S0038 | B11: 45293 | C11: 1 | D11: 1 | E11: January | F11: P010 | G11: Bottomwear | H11: 5 | I11: 425 | J11: 15 | K11: Track Pants | L11: 250 | M11: 2125 | N11: 1250 | O11: 875 | P11: 0.41176471 | Q11: 0 | R11: 0 | S11: 5 | T11: 2125
A12: S0062 | B12: 45294 | C12: 1 | D12: 1 | E12: January | F12: P010 | G12: Bottomwear | H12: 5 | I12: 500 | J12: 0 | K12: Track Pants | L12: 250 | M12: 2500 | N12: 1250 | O12: 1250 | P12: 0.5 | Q12: 0 | R12: 0 | S12: 5 | T12: 2500
A13: S0080 | B13: 45296 | C13: 1 | D13: 1 | E13: January | F13: P010 | G13: Bottomwear | H13: 1 | I13: 425 | J13: 15 | K13: Track Pants | L13: 250 | M13: 425 | N13: 250 | O13: 175 | P13: 0.41176471 | Q13: 0 | R13: 0 | S13: 1 | T13: 425
... A1501: S1397 | B1501: 45657 | C1501: 1 | D1501: 12 | E1501: December | F1501: P008 | G1501: Bottomwear | H1501: 1 | I1501: 1000 | J1501: 0 | K1501: Chino Trousers | L1501: 500 | M1501: 1000 | N1501: 500 | O1501: 500 | P1501: 0.5 | Q1501: 0 | R1501: 0 | S1501: 1 | T1501: 1000

Sheet Analysis
A1: MONTHLY METRICS | J1: RUNNING TOTALS | M1: MoM GROWTH | P1: WoW GROWTH | T1: 3-month moving average | W1: KPI Summary Block
A2: Month | B2: Month_Name | C2: Total_Units_Sold | D2: Total_Revenue_INR | E2: Net_Revenue_INR | F2: Total_COGS | G2: Gross_Profit | H2: Gross_Margin_% | J2: Month | K2: Cumulative Revenue | M2: Month | N2: MoM_Growth_% | P2: Week_Number | Q2: Weekly_Revenue | R2: WoW_Growth_% | T2: Month | U2: 3M_Moving_Avg | W2: Total Net Revenue | X2: =SUM(Sales_Master[Net_Revenue_INR]) -> 5428419.5
A3: 1 | B3: January | C3: =SUMIFS(Sales_Master[Units_Sold], Sales_Master[Month],A3) -> 442 | D3: =SUMIFS(Sales_Master[Revenue_INR],Sales_Master[Month],A3) -> 503070.5 | E3: =SUMIFS(Sales_Master[Net_Revenue_INR],Sales_Master[Month],A3) -> 469314.5 | F3: =SUMIFS(Sales_Master[Total_COGS],Sales_Master[Month],A3) -> 251380 | G3: =SUMIFS(Sales_Master[Gross_Profit],Sales_Master[Month],A3) -> 251690.5 | H3: =G3/D3 -> 0.5003086 | J3: 1 | K3: =SUMIFS(Sales_Master[Net_Revenue_INR],Sales_Master[Month],"<="&J3) -> 469314.5 | M3: 1 | N3: ="-" -> - | P3: 1 | Q3: =SUMIFS(Sales_Master[Net_Revenue_INR],Sales_Master[Week_Number],P3) -> 137464 | R3: ="-" -> - | T3: 1 | U3: ="-" -> - | W3: Total Units Sold | X3: =SUM(Sales_Master[Units_Sold]) -> 4491
A4: 2 | B4: February | C4: =SUMIFS(Sales_Master[Units_Sold], Sales_Master[Month],A4) -> 279 | D4: =SUMIFS(Sales_Master[Revenue_INR],Sales_Master[Month],A4) -> 428956 | E4: =SUMIFS(Sales_Master[Net_Revenue_INR],Sales_Master[Month],A4) -> 426889 | F4: =SUMIFS(Sales_Master[Total_COGS],Sales_Master[Month],A4) -> 207410 | G4: =SUMIFS(Sales_Master[Gross_Profit],Sales_Master[Month],A4) -> 221546 | H4: =G4/D4 -> 0.51647721 | J4: 2 | K4: =SUMIFS(Sales_Master[Net_Revenue_INR],Sales_Master[Month],"<="&J4) -> 896203.5 | M4: 2 | N4: =(E4-E3)/E3 -> -0.090398869 | P4: 2 | Q4: =SUMIFS(Sales_Master[Net_Revenue_INR],Sales_Master[Week_Number],P4) -> 104893.5 | R4: =(Q4-Q3)/Q3 -> -0.2369384 | T4: 2 | U4: ="-" -> - | W4: Avg Gross Margin | X4: =AVERAGE(H3:H14) -> 0.50158244
A5: 3 | B5: March | C5: =SUMIFS(Sales_Master[Units_Sold], Sales_Master[Month],A5) -> 293 | D5: =SUMIFS(Sales_Master[Revenue_INR],Sales_Master[Month],A5) -> 369205 | E5: =SUMIFS(Sales_Master[Net_Revenue_INR],Sales_Master[Month],A5) -> 354001 | F5: =SUMIFS(Sales_Master[Total_COGS],Sales_Master[Month],A5) -> 182760 | G5: =SUMIFS(Sales_Master[Gross_Profit],Sales_Master[Month],A5) -> 186445 | H5: =G5/D5 -> 0.50499045 | J5: 3 | K5: =SUMIFS(Sales_Master[Net_Revenue_INR],Sales_Master[Month],"<="&J5) -> 1250204.5 | M5: 3 | N5: =(E5-E4)/E4 -> -0.17074228 | P5: 3 | Q5: =SUMIFS(Sales_Master[Net_Revenue_INR],Sales_Master[Week_Number],P5) -> 99817 | R5: =(Q5-Q4)/Q4 -> -0.048396707 | T5: 3 | U5: =AVERAGE(E3:E5) -> 416734.83 | W5: Return Rate % | X5: =SUM(Sales_Master[Units_Returned_Clean])/SUM(Sales_Master[Units_Sold]) -> 0.048541527
A6: 4 | B6: April | C6: =SUMIFS(Sales_Master[Units_Sold], Sales_Master[Month],A6) -> 363 | D6: =SUMIFS(Sales_Master[Revenue_INR],Sales_Master[Month],A6) -> 439539 | E6: =SUMIFS(Sales_Master[Net_Revenue_INR],Sales_Master[Month],A6) -> 377846 | F6: =SUMIFS(Sales_Master[Total_COGS],Sales_Master[Month],A6) -> 212590 | G6: =SUMIFS(Sales_Master[Gross_Profit],Sales_Master[Month],A6) -> 226949 | H6: =G6/D6 -> 0.51633416 | J6: 4 | K6: =SUMIFS(Sales_Master[Net_Revenue_INR],Sales_Master[Month],"<="&J6) -> 1628050.5 | M6: 4 | N6: =(E6-E5)/E5 -> 0.067358567 | P6: 4 | Q6: =SUMIFS(Sales_Master[Net_Revenue_INR],Sales_Master[Week_Number],P6) -> 114903.5 | R6: =(Q6-Q5)/Q5 -> 0.15114159 | T6: 4 | U6: =AVERAGE(E4:E6) -> 386245.33 | W6: Best Month | X6: =INDEX(B3:B14,MATCH(MAX(E3:E14),E3:E14,0)) -> November
A7: 5 | B7: May | C7: =SUMIFS(Sales_Master[Units_Sold], Sales_Master[Month],A7) -> 377 | D7: =SUMIFS(Sales_Master[Revenue_INR],Sales_Master[Month],A7) -> 433028 | E7: =SUMIFS(Sales_Master[Net_Revenue_INR],Sales_Master[Month],A7) -> 399022 | F7: =SUMIFS(Sales_Master[Total_COGS],Sales_Master[Month],A7) -> 219920 | G7: =SUMIFS(Sales_Master[Gross_Profit],Sales_Master[Month],A7) -> 213108 | H7: =G7/D7 -> 0.49213446 | J7: 5 | K7: =SUMIFS(Sales_Master[Net_Revenue_INR],Sales_Master[Month],"<="&J7) -> 2027072.5 | M7: 5 | N7: =(E7-E6)/E6 -> 0.056043997 | P7: 5 | Q7: =SUMIFS(Sales_Master[Net_Revenue_INR],Sales_Master[Week_Number],P7) -> 91494 | R7: =(Q7-Q6)/Q6 -> -0.20373183 | T7: 5 | U7: =AVERAGE(E5:E7) -> 376956.33 | W7: Top Category | X7: =INDEX(G19:G24,MATCH(MAX(H19:H24),H19:H24,0)) -> Topwear
A8: 6 | B8: June | C8: =SUMIFS(Sales_Master[Units_Sold], Sales_Master[Month],A8) -> 371 | D8: =SUMIFS(Sales_Master[Revenue_INR],Sales_Master[Month],A8) -> 435714.5 | E8: =SUMIFS(Sales_Master[Net_Revenue_INR],Sales_Master[Month],A8) -> 407301.5 | F8: =SUMIFS(Sales_Master[Total_COGS],Sales_Master[Month],A8) -> 214800 | G8: =SUMIFS(Sales_Master[Gross_Profit],Sales_Master[Month],A8) -> 220914.5 | H8: =G8/D8 -> 0.50701664 | J8: 6 | K8: =SUMIFS(Sales_Master[Net_Revenue_INR],Sales_Master[Month],"<="&J8) -> 2434374 | M8: 6 | N8: =(E8-E7)/E7 -> 0.020749482 | P8: 6 | Q8: =SUMIFS(Sales_Master[Net_Revenue_INR],Sales_Master[Week_Number],P8) -> 143837 | R8: =(Q8-Q7)/Q7 -> 0.57209216 | T8: 6 | U8: =AVERAGE(E6:E8) -> 394723.17
A9: 7 | B9: July | C9: =SUMIFS(Sales_Master[Units_Sold], Sales_Master[Month],A9) -> 234 | D9: =SUMIFS(Sales_Master[Revenue_INR],Sales_Master[Month],A9) -> 356959 | E9: =SUMIFS(Sales_Master[Net_Revenue_INR],Sales_Master[Month],A9) -> 345535 | F9: =SUMIFS(Sales_Master[Total_COGS],Sales_Master[Month],A9) -> 177060 | G9: =SUMIFS(Sales_Master[Gross_Profit],Sales_Master[Month],A9) -> 179899 | H9: =G9/D9 -> 0.50397665 | J9: 7 | K9: =SUMIFS(Sales_Master[Net_Revenue_INR],Sales_Master[Month],"<="&J9) -> 2779909 | M9: 7 | N9: =(E9-E8)/E8 -> -0.1516481 | P9: 7 | Q9: =SUMIFS(Sales_Master[Net_Revenue_INR],Sales_Master[Week_Number],P9) -> 80795 | R9: =(Q9-Q8)/Q8 -> -0.43828778 | T9: 7 | U9: =AVERAGE(E7:E9) -> 383952.83
A10: 8 | B10: August | C10: =SUMIFS(Sales_Master[Units_Sold], Sales_Master[Month],A10) -> 263 | D10: =SUMIFS(Sales_Master[Revenue_INR],Sales_Master[Month],A10) -> 340673 | E10: =SUMIFS(Sales_Master[Net_Revenue_INR],Sales_Master[Month],A10) -> 321812 | F10: =SUMIFS(Sales_Master[Total_COGS],Sales_Master[Month],A10) -> 177590 | G10: =SUMIFS(Sales_Master[Gross_Profit],Sales_Master[Month],A10) -> 163083 | H10: =G10/D10 -> 0.47870832 | J10: 8 | K10: =SUMIFS(Sales_Master[Net_Revenue_INR],Sales_Master[Month],"<="&J10) -> 3101721 | M10: 8 | N10: =(E10-E9)/E9 -> -0.068655853 | P10: 8 | Q10: =SUMIFS(Sales_Master[Net_Revenue_INR],Sales_Master[Week_Number],P10) -> 73131.5 | R10: =(Q10-Q9)/Q9 -> -0.094851167 | T10: 8 | U10: =AVERAGE(E8:E10) -> 358216.17
A11: 9 | B11: September | C11: =SUMIFS(Sales_Master[Units_Sold], Sales_Master[Month],A11) -> 347 | D11: =SUMIFS(Sales_Master[Revenue_INR],Sales_Master[Month],A11) -> 464544.5 | E11: =SUMIFS(Sales_Master[Net_Revenue_INR],Sales_Master[Month],A11) -> 453764.5 | F11: =SUMIFS(Sales_Master[Total_COGS],Sales_Master[Month],A11) -> 228970 | G11: =SUMIFS(Sales_Master[Gross_Profit],Sales_Master[Month],A11) -> 235574.5 | H11: =G11/D11 -> 0.50710858 | J11: 9 | K11: =SUMIFS(Sales_Master[Net_Revenue_INR],Sales_Master[Month],"<="&J11) -> 3555485.5 | M11: 9 | N11: =(E11-E10)/E10 -> 0.41002977 | P11: 9 | Q11: =SUMIFS(Sales_Master[Net_Revenue_INR],Sales_Master[Week_Number],P11) -> 95268.5 | R11: =(Q11-Q10)/Q10 -> 0.3027013 | T11: 9 | U11: =AVERAGE(E9:E11) -> 373703.83
A12: 10 | B12: October | C12: =SUMIFS(Sales_Master[Units_Sold], Sales_Master[Month],A12) -> 496 | D12: =SUMIFS(Sales_Master[Revenue_INR],Sales_Master[Month],A12) -> 668522.5 | E12: =SUMIFS(Sales_Master[Net_Revenue_INR],Sales_Master[Month],A12) -> 625725.5 | F12: =SUMIFS(Sales_Master[Total_COGS],Sales_Master[Month],A12) -> 334650 | G12: =SUMIFS(Sales_Master[Gross_Profit],Sales_Master[Month],A12) -> 333872.5 | H12: =G12/D12 -> 0.49941849 | J12: 10 | K12: =SUMIFS(Sales_Master[Net_Revenue_INR],Sales_Master[Month],"<="&J12) -> 4181211 | M12: 10 | N12: =(E12-E11)/E11 -> 0.3789653 | P12: 10 | Q12: =SUMIFS(Sales_Master[Net_Revenue_INR],Sales_Master[Week_Number],P12) -> 66203 | R12: =(Q12-Q11)/Q11 -> -0.30509035 | T12: 10 | U12: =AVERAGE(E10:E12) -> 467100.67
A13: 11 | B13: November | C13: =SUMIFS(Sales_Master[Units_Sold], Sales_Master[Month],A13) -> 555 | D13: =SUMIFS(Sales_Master[Revenue_INR],Sales_Master[Month],A13) -> 742288.5 | E13: =SUMIFS(Sales_Master[Net_Revenue_INR],Sales_Master[Month],A13) -> 698527.5 | F13: =SUMIFS(Sales_Master[Total_COGS],Sales_Master[Month],A13) -> 377340 | G13: =SUMIFS(Sales_Master[Gross_Profit],Sales_Master[Month],A13) -> 364948.5 | H13: =G13/D13 -> 0.49165318 | J13: 11 | K13: =SUMIFS(Sales_Master[Net_Revenue_INR],Sales_Master[Month],"<="&J13) -> 4879738.5 | M13: 11 | N13: =(E13-E12)/E12 -> 0.11634814 | P13: 11 | Q13: =SUMIFS(Sales_Master[Net_Revenue_INR],Sales_Master[Week_Number],P13) -> 97104 | R13: =(Q13-Q12)/Q12 -> 0.46676133 | T13: 11 | U13: =AVERAGE(E11:E13) -> 592672.5
A14: 12 | B14: December | C14: =SUMIFS(Sales_Master[Units_Sold], Sales_Master[Month],A14) -> 471 | D14: =SUMIFS(Sales_Master[Revenue_INR],Sales_Master[Month],A14) -> 582024 | E14: =SUMIFS(Sales_Master[Net_Revenue_INR],Sales_Master[Month],A14) -> 548681 | F14: =SUMIFS(Sales_Master[Total_COGS],Sales_Master[Month],A14) -> 290510 | G14: =SUMIFS(Sales_Master[Gross_Profit],Sales_Master[Month],A14) -> 291514 | H14: =G14/D14 -> 0.50086251 | J14: 12 | K14: =SUMIFS(Sales_Master[Net_Revenue_INR],Sales_Master[Month],"<="&J14) -> 5428419.5 | M14: 12 | N14: =(E14-E13)/E13 -> -0.21451768 | P14: 12 | Q14: =SUMIFS(Sales_Master[Net_Revenue_INR],Sales_Master[Week_Number],P14) -> 94169.5 | R14: =(Q14-Q13)/Q13 -> -0.030220176 | T14: 12 | U14: =AVERAGE(E12:E14) -> 624311.33
P15: 13 | Q15: =SUMIFS(Sales_Master[Net_Revenue_INR],Sales_Master[Week_Number],P15) -> 72800.5 | R15: =(Q15-Q14)/Q14 -> -0.22692061
P16: 14 | Q16: =SUMIFS(Sales_Master[Net_Revenue_INR],Sales_Master[Week_Number],P16) -> 81632 | R16: =(Q16-Q15)/Q15 -> 0.12131098
A17: TOP 5 PRODUCTS | F17: TOP 5 CATEGORIES | P17: 15 | Q17: =SUMIFS(Sales_Master[Net_Revenue_INR],Sales_Master[Week_Number],P17) -> 110638.5 | R17: =(Q17-Q16)/Q16 -> 0.35533247
A18: Rank | B18: Product_Name | C18: Total_Revenue | D18: % of Total | F18: Rank | G18: Category | H18: Total_Revenue | I18: Gross_Margin_% | P18: 16 | Q18: =SUMIFS(Sales_Master[Net_Revenue_INR],Sales_Master[Week_Number],P18) -> 69786.5 | R18: =(Q18-Q17)/Q17 -> -0.36923856
A19: 1 | B19: =INDEX($B$33:$B$62,MATCH(C19,$C$33:$C$62,0)) -> Wrist Watch | C19: =LARGE($C$33:$C$62,A19) -> 812925 | D19: =C19/SUM($C$33:$C$62) -> 0.14975353 | G19: Topwear | H19: =SUMIFS(Sales_Master[Net_Revenue_INR],Sales_Master[Category],G19) -> 1352934.5 | I19: =SUMIFS(Sales_Master[Gross_Profit],Sales_Master[Category],G19)/H19 -> 0.55889365 | P19: 17 | Q19: =SUMIFS(Sales_Master[Net_Revenue_INR],Sales_Master[Week_Number],P19) -> 98429 | R19: =(Q19-Q18)/Q18 -> 0.41043038
A20: 2 | B20: =INDEX($B$33:$B$62,MATCH(C20,$C$33:$C$62,0)) -> Ethnic Sherwani | C20: =LARGE($C$33:$C$62,A20) -> 566280 | D20: =C20/SUM($C$33:$C$62) -> 0.10431766 | G20: Bottomwear | H20: =SUMIFS(Sales_Master[Net_Revenue_INR],Sales_Master[Category],G20) -> 574800 | I20: =SUMIFS(Sales_Master[Gross_Profit],Sales_Master[Category],G20)/H20 -> 0.50618476 | P20: 18 | Q20: =SUMIFS(Sales_Master[Net_Revenue_INR],Sales_Master[Week_Number],P20) -> 81315 | R20: =(Q20-Q19)/Q19 -> -0.17387152
A21: 3 | B21: =INDEX($B$33:$B$62,MATCH(C21,$C$33:$C$62,0)) -> Formal Blazer | C21: =LARGE($C$33:$C$62,A21) -> 378048 | D21: =C21/SUM($C$33:$C$62) -> 0.06964237 | G21: Footwear | H21: =SUMIFS(Sales_Master[Net_Revenue_INR],Sales_Master[Category],G21) -> 1008900 | I21: =SUMIFS(Sales_Master[Gross_Profit],Sales_Master[Category],G21)/H21 -> 0.43807018 | P21: 19 | Q21: =SUMIFS(Sales_Master[Net_Revenue_INR],Sales_Master[Week_Number],P21) -> 92455 | R21: =(Q21-Q20)/Q20 -> 0.13699809
A22: 4 | B22: =INDEX($B$33:$B$62,MATCH(C22,$C$33:$C$62,0)) -> Quilted Jacket | C22: =LARGE($C$33:$C$62,A22) -> 359415 | D22: =C22/SUM($C$33:$C$62) -> 0.066209879 | G22: Accessories | H22: =SUMIFS(Sales_Master[Net_Revenue_INR],Sales_Master[Category],G22) -> 1253172 | I22: =SUMIFS(Sales_Master[Gross_Profit],Sales_Master[Category],G22)/H22 -> 0.60919251 | P22: 20 | Q22: =SUMIFS(Sales_Master[Net_Revenue_INR],Sales_Master[Week_Number],P22) -> 83151 | R22: =(Q22-Q21)/Q21 -> -0.10063274
A23: 5 | B23: =INDEX($B$33:$B$62,MATCH(C23,$C$33:$C$62,0)) -> Running Sneakers | C23: =LARGE($C$33:$C$62,A23) -> 320364 | D23: =C23/SUM($C$33:$C$62) -> 0.059016073 | G23: Winter Collection | H23: =SUMIFS(Sales_Master[Net_Revenue_INR],Sales_Master[Category],G23) -> 939186 | I23: =SUMIFS(Sales_Master[Gross_Profit],Sales_Master[Category],G23)/H23 -> 0.51756521 | P23: 21 | Q23: =SUMIFS(Sales_Master[Net_Revenue_INR],Sales_Master[Week_Number],P23) -> 92048 | R23: =(Q23-Q22)/Q22 -> 0.10699811
G24: Summer Collection | H24: =SUMIFS(Sales_Master[Net_Revenue_INR],Sales_Master[Category],G24) -> 299427 | I24: =SUMIFS(Sales_Master[Gross_Profit],Sales_Master[Category],G24)/H24 -> 0.50416629 | P24: 22 | Q24: =SUMIFS(Sales_Master[Net_Revenue_INR],Sales_Master[Week_Number],P24) -> 85119.5 | R24: =(Q24-Q23)/Q23 -> -0.075270511
P25: 23 | Q25: =SUMIFS(Sales_Master[Net_Revenue_INR],Sales_Master[Week_Number],P25) -> 80625 | R25: =(Q25-Q24)/Q24 -> -0.052802237
P26: 24 | Q26: =SUMIFS(Sales_Master[Net_Revenue_INR],Sales_Master[Week_Number],P26) -> 130420 | R26: =(Q26-Q25)/Q25 -> 0.6176124
F27: BUDGET VS ACTUAL | P27: 25 | Q27: =SUMIFS(Sales_Master[Net_Revenue_INR],Sales_Master[Week_Number],P27) -> 82782 | R27: =(Q27-Q26)/Q26 -> -0.36526606
F28: Month | G28: Month_Name | H28: Actual_Revenue | I28: Budgeted_Revenue | J28: Variance_INR | K28: Variance_% | L28: Status | P28: 26 | Q28: =SUMIFS(Sales_Master[Net_Revenue_INR],Sales_Master[Week_Number],P28) -> 95768 | R28: =(Q28-Q27)/Q27 -> 0.15686985
F29: 1 | G29: January | H29: =SUMIFS(Sales_Master[Net_Revenue_INR],Sales_Master[Month],F29) -> 469314.5 | I29: =SUMIFS(tbl_Budget[Budgeted_Revenue_INR],tbl_Budget[Month],F29) -> 499300 | J29: =H29-I29 -> -29985.5 | K29: =J29/I29 -> -0.060055077 | L29: =IF(J29>0,"✅ Over","❌ Under") -> ❌ Under | P29: 27 | Q29: =SUMIFS(Sales_Master[Net_Revenue_INR],Sales_Master[Week_Number],P29) -> 69297 | R29: =(Q29-Q28)/Q28 -> -0.27640757
F30: 2 | G30: February | H30: =SUMIFS(Sales_Master[Net_Revenue_INR],Sales_Master[Month],F30) -> 426889 | I30: =SUMIFS(tbl_Budget[Budgeted_Revenue_INR],tbl_Budget[Month],F30) -> 457400 | J30: =H30-I30 -> -30511 | K30: =J30/I30 -> -0.066705291 | L30: =IF(J30>0,"✅ Over","❌ Under") -> ❌ Under | P30: 28 | Q30: =SUMIFS(Sales_Master[Net_Revenue_INR],Sales_Master[Week_Number],P30) -> 81195 | R30: =(Q30-Q29)/Q29 -> 0.17169574
A31: Helper Table | F31: 3 | G31: March | H31: =SUMIFS(Sales_Master[Net_Revenue_INR],Sales_Master[Month],F31) -> 354001 | I31: =SUMIFS(tbl_Budget[Budgeted_Revenue_INR],tbl_Budget[Month],F31) -> 377000 | J31: =H31-I31 -> -22999 | K31: =J31/I31 -> -0.061005305 | L31: =IF(J31>0,"✅ Over","❌ Under") -> ❌ Under | P31: 29 | Q31: =SUMIFS(Sales_Master[Net_Revenue_INR],Sales_Master[Week_Number],P31) -> 57168 | R31: =(Q31-Q30)/Q30 -> -0.29591724
A32: Product_ID | B32: Product_Name | C32: Product_Revenue | F32: 4 | G32: April | H32: =SUMIFS(Sales_Master[Net_Revenue_INR],Sales_Master[Month],F32) -> 377846 | I32: =SUMIFS(tbl_Budget[Budgeted_Revenue_INR],tbl_Budget[Month],F32) -> 439100 | J32: =H32-I32 -> -61254 | K32: =J32/I32 -> -0.13949898 | L32: =IF(J32>0,"✅ Over","❌ Under") -> ❌ Under | P32: 30 | Q32: =SUMIFS(Sales_Master[Net_Revenue_INR],Sales_Master[Week_Number],P32) -> 91299 | R32: =(Q32-Q31)/Q31 -> 0.59702981
A33: P001 | B33: =INDEX(Sales_Master[Product_Name],MATCH(A33,Sales_Master[Product_ID],0)) -> Classic Cotton Kurta | C33: =SUMIFS(Sales_Master[Net_Revenue_INR],Sales_Master[Product_ID],A33) -> 126934.5 | F33: 5 | G33: May | H33: =SUMIFS(Sales_Master[Net_Revenue_INR],Sales_Master[Month],F33) -> 399022 | I33: =SUMIFS(tbl_Budget[Budgeted_Revenue_INR],tbl_Budget[Month],F33) -> 429400 | J33: =H33-I33 -> -30378 | K33: =J33/I33 -> -0.070745226 | L33: =IF(J33>0,"✅ Over","❌ Under") -> ❌ Under | P33: 31 | Q33: =SUMIFS(Sales_Master[Net_Revenue_INR],Sales_Master[Week_Number],P33) -> 94287 | R33: =(Q33-Q32)/Q32 -> 0.032727631
A34: P002 | B34: =INDEX(Sales_Master[Product_Name],MATCH(A34,Sales_Master[Product_ID],0)) -> Slim Fit Shirt | C34: =SUMIFS(Sales_Master[Net_Revenue_INR],Sales_Master[Product_ID],A34) -> 137060 | F34: 6 | G34: June | H34: =SUMIFS(Sales_Master[Net_Revenue_INR],Sales_Master[Month],F34) -> 407301.5 | I34: =SUMIFS(tbl_Budget[Budgeted_Revenue_INR],tbl_Budget[Month],F34) -> 470200 | J34: =H34-I34 -> -62898.5 | K34: =J34/I34 -> -0.13376967 | L34: =IF(J34>0,"✅ Over","❌ Under") -> ❌ Under | P34: 32 | Q34: =SUMIFS(Sales_Master[Net_Revenue_INR],Sales_Master[Week_Number],P34) -> 48026 | R34: =(Q34-Q33)/Q33 -> -0.49064028
A35: P003 | B35: =INDEX(Sales_Master[Product_Name],MATCH(A35,Sales_Master[Product_ID],0)) -> Casual T-Shirt | C35: =SUMIFS(Sales_Master[Net_Revenue_INR],Sales_Master[Product_ID],A35) -> 67620 | F35: 7 | G35: July | H35: =SUMIFS(Sales_Master[Net_Revenue_INR],Sales_Master[Month],F35) -> 345535 | I35: =SUMIFS(tbl_Budget[Budgeted_Revenue_INR],tbl_Budget[Month],F35) -> 370800 | J35: =H35-I35 -> -25265 | K35: =J35/I35 -> -0.068136462 | L35: =IF(J35>0,"✅ Over","❌ Under") -> ❌ Under | P35: 33 | Q35: =SUMIFS(Sales_Master[Net_Revenue_INR],Sales_Master[Week_Number],P35) -> 119890 | R35: =(Q35-Q34)/Q34 -> 1.4963561
A36: P004 | B36: =INDEX(Sales_Master[Product_Name],MATCH(A36,Sales_Master[Product_ID],0)) -> Formal Blazer | C36: =SUMIFS(Sales_Master[Net_Revenue_INR],Sales_Master[Product_ID],A36) -> 378048 | F36: 8 | G36: August | H36: =SUMIFS(Sales_Master[Net_Revenue_INR],Sales_Master[Month],F36) -> 321812 | I36: =SUMIFS(tbl_Budget[Budgeted_Revenue_INR],tbl_Budget[Month],F36) -> 343800 | J36: =H36-I36 -> -21988 | K36: =J36/I36 -> -0.063955788 | L36: =IF(J36>0,"✅ Over","❌ Under") -> ❌ Under | P36: 34 | Q36: =SUMIFS(Sales_Master[Net_Revenue_INR],Sales_Master[Week_Number],P36) -> 23628 | R36: =(Q36-Q35)/Q35 -> -0.80291934
A37: P005 | B37: =INDEX(Sales_Master[Product_Name],MATCH(A37,Sales_Master[Product_ID],0)) -> Ethnic Sherwani | C37: =SUMIFS(Sales_Master[Net_Revenue_INR],Sales_Master[Product_ID],A37) -> 566280 | F37: 9 | G37: September | H37: =SUMIFS(Sales_Master[Net_Revenue_INR],Sales_Master[Month],F37) -> 453764.5 | I37: =SUMIFS(tbl_Budget[Budgeted_Revenue_INR],tbl_Budget[Month],F37) -> 484200 | J37: =H37-I37 -> -30435.5 | K37: =J37/I37 -> -0.06285729 | L37: =IF(J37>0,"✅ Over","❌ Under") -> ❌ Under | P37: 35 | Q37: =SUMIFS(Sales_Master[Net_Revenue_INR],Sales_Master[Week_Number],P37) -> 85377 | R37: =(Q37-Q36)/Q36 -> 2.6133824
A38: P006 | B38: =INDEX(Sales_Master[Product_Name],MATCH(A38,Sales_Master[Product_ID],0)) -> Polo Neck Tee | C38: =SUMIFS(Sales_Master[Net_Revenue_INR],Sales_Master[Product_ID],A38) -> 76992 | F38: 10 | G38: October | H38: =SUMIFS(Sales_Master[Net_Revenue_INR],Sales_Master[Month],F38) -> 625725.5 | I38: =SUMIFS(tbl_Budget[Budgeted_Revenue_INR],tbl_Budget[Month],F38) -> 703400 | J38: =H38-I38 -> -77674.5 | K38: =J38/I38 -> -0.11042721 | L38: =IF(J38>0,"✅ Over","❌ Under") -> ❌ Under | P38: 36 | Q38: =SUMIFS(Sales_Master[Net_Revenue_INR],Sales_Master[Week_Number],P38) -> 133456 | R38: =(Q38-Q37)/Q37 -> 0.56313761
A39: P007 | B39: =INDEX(Sales_Master[Product_Name],MATCH(A39,Sales_Master[Product_ID],0)) -> Slim Fit Jeans | C39: =SUMIFS(Sales_Master[Net_Revenue_INR],Sales_Master[Product_ID],A39) -> 162300 | F39: 11 | G39: November | H39: =SUMIFS(Sales_Master[Net_Revenue_INR],Sales_Master[Month],F39) -> 698527.5 | I39: =SUMIFS(tbl_Budget[Budgeted_Revenue_INR],tbl_Budget[Month],F39) -> 813700 | J39: =H39-I39 -> -115172.5 | K39: =J39/I39 -> -0.14154172 | L39: =IF(J39>0,"✅ Over","❌ Under") -> ❌ Under | P39: 37 | Q39: =SUMIFS(Sales_Master[Net_Revenue_INR],Sales_Master[Week_Number],P39) -> 85495.5 | R39: =(Q39-Q38)/Q38 -> -0.35937313
A40: P008 | B40: =INDEX(Sales_Master[Product_Name],MATCH(A40,Sales_Master[Product_ID],0)) -> Chino Trousers | C40: =SUMIFS(Sales_Master[Net_Revenue_INR],Sales_Master[Product_ID],A40) -> 117900 | F40: 12 | G40: December | H40: =SUMIFS(Sales_Master[Net_Revenue_INR],Sales_Master[Month],F40) -> 548681 | I40: =SUMIFS(tbl_Budget[Budgeted_Revenue_INR],tbl_Budget[Month],F40) -> 624100 | J40: =H40-I40 -> -75419 | K40: =J40/I40 -> -0.12084442 | L40: =IF(J40>0,"✅ Over","❌ Under") -> ❌ Under | P40: 38 | Q40: =SUMIFS(Sales_Master[Net_Revenue_INR],Sales_Master[Week_Number],P40) -> 132318 | R40: =(Q40-Q39)/Q39 -> 0.5476604
A41: P009 | B41: =INDEX(Sales_Master[Product_Name],MATCH(A41,Sales_Master[Product_ID],0)) -> Ethnic Pyjama | C41: =SUMIFS(Sales_Master[Net_Revenue_INR],Sales_Master[Product_ID],A41) -> 73650 | P41: 39 | Q41: =SUMIFS(Sales_Master[Net_Revenue_INR],Sales_Master[Week_Number],P41) -> 75798 | R41: =(Q41-Q40)/Q40 -> -0.42715277
A42: P010 | B42: =INDEX(Sales_Master[Product_Name],MATCH(A42,Sales_Master[Product_ID],0)) -> Track Pants | C42: =SUMIFS(Sales_Master[Net_Revenue_INR],Sales_Master[Product_ID],A42) -> 64150 | P42: 40 | Q42: =SUMIFS(Sales_Master[Net_Revenue_INR],Sales_Master[Week_Number],P42) -> 125934 | R42: =(Q42-Q41)/Q41 -> 0.66144225
A43: P011 | B43: =INDEX(Sales_Master[Product_Name],MATCH(A43,Sales_Master[Product_ID],0)) -> Formal Trousers | C43: =SUMIFS(Sales_Master[Net_Revenue_INR],Sales_Master[Product_ID],A43) -> 156800 | P43: 41 | Q43: =SUMIFS(Sales_Master[Net_Revenue_INR],Sales_Master[Week_Number],P43) -> 146806 | R43: =(Q43-Q42)/Q42 -> 0.16573761
A44: P012 | B44: =INDEX(Sales_Master[Product_Name],MATCH(A44,Sales_Master[Product_ID],0)) -> Leather Loafers | C44: =SUMIFS(Sales_Master[Net_Revenue_INR],Sales_Master[Product_ID],A44) -> 226719 | P44: 42 | Q44: =SUMIFS(Sales_Master[Net_Revenue_INR],Sales_Master[Week_Number],P44) -> 152031 | R44: =(Q44-Q43)/Q43 -> 0.035591188
A45: P013 | B45: =INDEX(Sales_Master[Product_Name],MATCH(A45,Sales_Master[Product_ID],0)) -> Running Sneakers | C45: =SUMIFS(Sales_Master[Net_Revenue_INR],Sales_Master[Product_ID],A45) -> 320364 | P45: 43 | Q45: =SUMIFS(Sales_Master[Net_Revenue_INR],Sales_Master[Week_Number],P45) -> 145571 | R45: =(Q45-Q44)/Q44 -> -0.042491334
A46: P014 | B46: =INDEX(Sales_Master[Product_Name],MATCH(A46,Sales_Master[Product_ID],0)) -> Ethnic Juttis | C46: =SUMIFS(Sales_Master[Net_Revenue_INR],Sales_Master[Product_ID],A46) -> 121995 | P46: 44 | Q46: =SUMIFS(Sales_Master[Net_Revenue_INR],Sales_Master[Week_Number],P46) -> 159371.5 | R46: =(Q46-Q45)/Q45 -> 0.094802536
A47: P015 | B47: =INDEX(Sales_Master[Product_Name],MATCH(A47,Sales_Master[Product_ID],0)) -> Casual Sandals | C47: =SUMIFS(Sales_Master[Net_Revenue_INR],Sales_Master[Product_ID],A47) -> 94941 | P47: 45 | Q47: =SUMIFS(Sales_Master[Net_Revenue_INR],Sales_Master[Week_Number],P47) -> 176026 | R47: =(Q47-Q46)/Q46 -> 0.10450112
A48: P016 | B48: =INDEX(Sales_Master[Product_Name],MATCH(A48,Sales_Master[Product_ID],0)) -> Formal Oxford Shoes | C48: =SUMIFS(Sales_Master[Net_Revenue_INR],Sales_Master[Product_ID],A48) -> 244881 | P48: 46 | Q48: =SUMIFS(Sales_Master[Net_Revenue_INR],Sales_Master[Week_Number],P48) -> 178682 | R48: =(Q48-Q47)/Q47 -> 0.01508868
A49: P017 | B49: =INDEX(Sales_Master[Product_Name],MATCH(A49,Sales_Master[Product_ID],0)) -> Leather Belt | C49: =SUMIFS(Sales_Master[Net_Revenue_INR],Sales_Master[Product_ID],A49) -> 71925 | P49: 47 | Q49: =SUMIFS(Sales_Master[Net_Revenue_INR],Sales_Master[Week_Number],P49) -> 115402.5 | R49: =(Q49-Q48)/Q48 -> -0.35414591
A50: P018 | B50: =INDEX(Sales_Master[Product_Name],MATCH(A50,Sales_Master[Product_ID],0)) -> Silk Pocket Square | C50: =SUMIFS(Sales_Master[Net_Revenue_INR],Sales_Master[Product_ID],A50) -> 44897 | P50: 48 | Q50: =SUMIFS(Sales_Master[Net_Revenue_INR],Sales_Master[Week_Number],P50) -> 157486 | R50: =(Q50-Q49)/Q49 -> 0.36466714
A51: P019 | B51: =INDEX(Sales_Master[Product_Name],MATCH(A51,Sales_Master[Product_ID],0)) -> Wrist Watch | C51: =SUMIFS(Sales_Master[Net_Revenue_INR],Sales_Master[Product_ID],A51) -> 812925 | P51: 49 | Q51: =SUMIFS(Sales_Master[Net_Revenue_INR],Sales_Master[Week_Number],P51) -> 107791.5 | R51: =(Q51-Q50)/Q50 -> -0.31554868
A52: P020 | B52: =INDEX(Sales_Master[Product_Name],MATCH(A52,Sales_Master[Product_ID],0)) -> Sunglasses | C52: =SUMIFS(Sales_Master[Net_Revenue_INR],Sales_Master[Product_ID],A52) -> 207825 | P52: 50 | Q52: =SUMIFS(Sales_Master[Net_Revenue_INR],Sales_Master[Week_Number],P52) -> 143300 | R52: =(Q52-Q51)/Q51 -> 0.32941837
... A54: P022 | B54: =INDEX(Sales_Master[Product_Name],MATCH(A54,Sales_Master[Product_ID],0)) -> Woolen Sweater | C54: =SUMIFS(Sales_Master[Net_Revenue_INR],Sales_Master[Product_ID],A54) -> 164787 | P54: 52 | Q54: =SUMIFS(Sales_Master[Net_Revenue_INR],Sales_Master[Week_Number],P54) -> 122089.5 | R54: =(Q54-Q53)/Q53 -> -0.1559282
A55: P023 | B55: =INDEX(Sales_Master[Product_Name],MATCH(A55,Sales_Master[Product_ID],0)) -> Quilted Jacket | C55: =SUMIFS(Sales_Master[Net_Revenue_INR],Sales_Master[Product_ID],A55) -> 359415
A56: P024 | B56: =INDEX(Sales_Master[Product_Name],MATCH(A56,Sales_Master[Product_ID],0)) -> Fleece Hoodie | C56: =SUMIFS(Sales_Master[Net_Revenue_INR],Sales_Master[Product_ID],A56) -> 203616
A57: P025 | B57: =INDEX(Sales_Master[Product_Name],MATCH(A57,Sales_Master[Product_ID],0)) -> Thermal Innerwear Set | C57: =SUMIFS(Sales_Master[Net_Revenue_INR],Sales_Master[Product_ID],A57) -> 126712
A58: P026 | B58: =INDEX(Sales_Master[Product_Name],MATCH(A58,Sales_Master[Product_ID],0)) -> Woolen Muffler | C58: =SUMIFS(Sales_Master[Net_Revenue_INR],Sales_Master[Product_ID],A58) -> 84656
A59: P027 | B59: =INDEX(Sales_Master[Product_Name],MATCH(A59,Sales_Master[Product_ID],0)) -> Linen Shirt | C59: =SUMIFS(Sales_Master[Net_Revenue_INR],Sales_Master[Product_ID],A59) -> 89712
A60: P028 | B60: =INDEX(Sales_Master[Product_Name],MATCH(A60,Sales_Master[Product_ID],0)) -> Cotton Shorts | C60: =SUMIFS(Sales_Master[Net_Revenue_INR],Sales_Master[Product_ID],A60) -> 73740
A61: P029 | B61: =INDEX(Sales_Master[Product_Name],MATCH(A61,Sales_Master[Product_ID],0)) -> Sleeveless Vest | C61: =SUMIFS(Sales_Master[Net_Revenue_INR],Sales_Master[Product_ID],A61) -> 55300
A62: P030 | B62: =INDEX(Sales_Master[Product_Name],MATCH(A62,Sales_Master[Product_ID],0)) -> Breathable Joggers | C62: =SUMIFS(Sales_Master[Net_Revenue_INR],Sales_Master[Product_ID],A62) -> 80675

Sheet Pivot_Data
A1: PT1 — Monthly Revenue Trend
A2: Row Labels | B2: Total Revenue
A3: January | B3: 469314.5
A4: February | B4: 426889
A5: March | B5: 354001
A6: April | B6: 377846
A7: May | B7: 399022
A8: June | B8: 407301.5
A9: July | B9: 345535
A10: August | B10: 321812
A11: September | B11: 453764.5
A12: October | B12: 625725.5
A13: November | B13: 698527.5
A14: December | B14: 548681
A15: Grand Total | B15: 5428419.5
A20: PT2 — Category Performance | H20: PT-2 - For Chart
A21: Row Labels | B21: Total_Revenue | C21: Sum of Gross_Profit | D21: Sum of Units_Sold | E21: Sum of Margin_% | H21: Row Labels | I21: Total_Revenue
A22: Topwear | B22: 1352934.5 | C22: 756146.5 | D22: 1035 | E22: 0.51796657 | H22: Topwear | I22: 1352934.5
A23: Accessories | B23: 1253172 | C23: 763423 | D23: 772 | E23: 0.57583236 | H23: Accessories | I23: 1253172
A24: Footwear | B24: 1008900 | C24: 441969 | D24: 758 | E24: 0.41655145 | H24: Footwear | I24: 1008900
A25: Winter Collection | B25: 939186 | C25: 486090 | D25: 702 | E25: 0.49741108 | H25: Winter Collection | I25: 939186
A26: Bottomwear | B26: 574800 | C26: 290955 | D26: 702 | E26: 0.46765677 | H26: Bottomwear | I26: 574800
A27: Summer Collection | B27: 299427 | C27: 150961 | D27: 522 | E27: 0.47397339 | H27: Summer Collection | I27: 299427
A28: Grand Total | B28: 5428419.5 | C28: 2889544.5 | D28: 4491 | E28: 0.50126329 | H28: Grand Total | I28: 5428419.5
A35: PT3 — Top 10 Products | H35: PT3 - For Chart
A36: Row Labels | B36: Revenue | C36: Sum of Units_Sold | H36: Row Labels | I36: Sum of Net_Revenue_INR
A37: Wrist Watch | B37: 812925 | C37: 206 | H37: Wrist Watch | I37: 812925
A38: Ethnic Sherwani | B38: 566280 | C38: 155 | H38: Ethnic Sherwani | I38: 566280
A39: Formal Blazer | B39: 378048 | C39: 155 | H39: Formal Blazer | I39: 378048
A40: Quilted Jacket | B40: 359415 | C40: 129 | H40: Quilted Jacket | I40: 359415
A41: Running Sneakers | B41: 320364 | C41: 178 | H41: Running Sneakers | I41: 320364
A42: Formal Oxford Shoes | B42: 244881 | C42: 120 | H42: Grand Total | I42: 2437032
A43: Leather Loafers | B43: 226719 | C43: 152
A44: Sunglasses | B44: 207825 | C44: 148
A45: Fleece Hoodie | B45: 203616 | C45: 129
A46: Woolen Sweater | B46: 164787 | C46: 121
A47: Grand Total | B47: 3484860 | C47: 1493
A60: PT4 — Budget vs Actual
A61: Month_Name | B61: Actual | C61: Budgeted
A62: =Analysis!G29 -> January | B62: =Analysis!H29 -> 469314.5 | C62: =Analysis!I29 -> 499300
A63: =Analysis!G30 -> February | B63: =Analysis!H30 -> 426889 | C63: =Analysis!I30 -> 457400
A64: =Analysis!G31 -> March | B64: =Analysis!H31 -> 354001 | C64: =Analysis!I31 -> 377000
A65: =Analysis!G32 -> April | B65: =Analysis!H32 -> 377846 | C65: =Analysis!I32 -> 439100
A66: =Analysis!G33 -> May | B66: =Analysis!H33 -> 399022 | C66: =Analysis!I33 -> 429400
A67: =Analysis!G34 -> June | B67: =Analysis!H34 -> 407301.5 | C67: =Analysis!I34 -> 470200
A68: =Analysis!G35 -> July | B68: =Analysis!H35 -> 345535 | C68: =Analysis!I35 -> 370800
A69: =Analysis!G36 -> August | B69: =Analysis!H36 -> 321812 | C69: =Analysis!I36 -> 343800
A70: =Analysis!G37 -> September | B70: =Analysis!H37 -> 453764.5 | C70: =Analysis!I37 -> 484200
A71: =Analysis!G38 -> October | B71: =Analysis!H38 -> 625725.5 | C71: =Analysis!I38 -> 703400
A72: =Analysis!G39 -> November | B72: =Analysis!H39 -> 698527.5 | C72: =Analysis!I39 -> 813700
A73: =Analysis!G40 -> December | B73: =Analysis!H40 -> 548681 | C73: =Analysis!I40 -> 624100
A80: PT5 — Weekly Revenue
A81: Row Labels | B81: Sum of Net_Revenue_INR
A82: 1 | B82: 137464
A83: 2 | B83: 104893.5
A84: 3 | B84: 99817
A85: 4 | B85: 114903.5
A86: 5 | B86: 91494
A87: 6 | B87: 143837
A88: 7 | B88: 80795
A89: 8 | B89: 73131.5
A90: 9 | B90: 95268.5
A91: 10 | B91: 66203
A92: 11 | B92: 97104
A93: 12 | B93: 94169.5
... A133: 52 | B133: 122089.5
A134: Grand Total | B134: 5428419.5
A140: PT6 — Category x Month Matrix
A141: Sum of Net_Revenue_INR | B141: Column Labels | L141: REVENUE HEATMAP — CATEGORY x MONTH
A142: Row Labels | B142: Accessories | C142: Bottomwear | D142: Footwear | E142: Summer Collection | F142: Topwear | G142: Winter Collection | H142: Grand Total | M142: Accessories | N142: Bottomwear | O142: Footwear | P142: Summer Collection | Q142: Topwear | R142: Winter Collection
A143: January | B143: 92534 | C143: 92800 | D143: 74880 | F143: 69616 | G143: 139484.5 | H143: 469314.5 | L143: January | M143: 92534 | N143: 92800 | O143: 74880 | Q143: 69616 | R143: 139484.5
A144: February | B144: 152427 | C144: 41000 | D144: 65596.5 | E144: 2280 | F144: 59597 | G144: 105988.5 | H144: 426889 | L144: February | M144: 152427 | N144: 41000 | O144: 65596.5 | P144: 2280 | Q144: 59597 | R144: 105988.5
A145: March | B145: 99213 | C145: 29210 | D145: 69898.5 | E145: 47645 | F145: 69157 | G145: 38877.5 | H145: 354001 | L145: March | M145: 99213 | N145: 29210 | O145: 69898.5 | P145: 47645 | Q145: 69157 | R145: 38877.5
A146: April | B146: 111857 | C146: 47920 | D146: 50427 | E146: 46440 | F146: 79740.5 | G146: 41461.5 | H146: 377846 | L146: April | M146: 111857 | N146: 47920 | O146: 50427 | P146: 46440 | Q146: 79740.5 | R146: 41461.5
A147: May | B147: 98605 | C147: 32915 | D147: 109854 | E147: 61996 | F147: 88302 | G147: 7350 | H147: 399022 | L147: May | M147: 98605 | N147: 32915 | O147: 109854 | P147: 61996 | Q147: 88302 | R147: 7350
A148: June | B148: 74157 | C148: 40825 | D148: 58320 | E148: 58039 | F148: 170080.5 | G148: 5880 | H148: 407301.5 | L148: June | M148: 74157 | N148: 40825 | O148: 58320 | P148: 58039 | Q148: 170080.5 | R148: 5880
A149: July | B149: 116202 | C149: 34480 | D149: 81630 | E149: 18911 | F149: 88143 | G149: 6169 | H149: 345535 | L149: July | M149: 116202 | N149: 34480 | O149: 81630 | P149: 18911 | Q149: 88143 | R149: 6169
A150: August | B150: 33488 | C150: 55815 | D150: 87408 | E150: 16653 | F150: 127928 | G150: 520 | H150: 321812 | L150: August | M150: 33488 | N150: 55815 | O150: 87408 | P150: 16653 | Q150: 127928 | R150: 520
A151: September | B151: 128335 | C151: 45205 | D151: 66897 | E151: 18653 | F151: 105608 | G151: 89066.5 | H151: 453764.5 | L151: September | M151: 128335 | N151: 45205 | O151: 66897 | P151: 18653 | Q151: 105608 | R151: 89066.5
A152: October | B152: 103589 | C152: 53650 | D152: 88911 | E152: 27220 | F152: 239565.5 | G152: 112790 | H152: 625725.5 | L152: October | M152: 103589 | N152: 53650 | O152: 88911 | P152: 27220 | Q152: 239565.5 | R152: 112790
A153: November | B153: 110578 | C153: 51730 | D153: 174145.5 | F153: 164824.5 | G153: 197249.5 | H153: 698527.5 | L153: November | M153: 110578 | N153: 51730 | O153: 174145.5 | Q153: 164824.5 | R153: 197249.5
A154: December | B154: 132187 | C154: 49250 | D154: 80932.5 | E154: 1590 | F154: 90372.5 | G154: 194349 | H154: 548681 | L154: December | M154: 132187 | N154: 49250 | O154: 80932.5 | P154: 1590 | Q154: 90372.5 | R154: 194349
A155: Grand Total | B155: 1253172 | C155: 574800 | D155: 1008900 | E155: 299427 | F155: 1352934.5 | G155: 939186 | H155: 5428419.5
A165: PT7 — Returns Analysis | G165: PT7- For Chart
A166: Row Labels | B166: Total_Returns | C166: Total_Sold | D166: Sum of Return_Rate_% | G166: Row Labels | H166: Sum of Return_Rate_%
A167: Bottomwear | B167: 46 | C167: 702 | D167: 0.065527066 | G167: Winter Collection | H167: 0.028490028
A168: Topwear | B168: 60 | C168: 1035 | D168: 0.057971014 | G168: Footwear | H168: 0.039577836
A169: Summer Collection | B169: 27 | C169: 522 | D169: 0.051724138 | G169: Accessories | H169: 0.045336788
A170: Accessories | B170: 35 | C170: 772 | D170: 0.045336788 | G170: Summer Collection | H170: 0.051724138
A171: Footwear | B171: 30 | C171: 758 | D171: 0.039577836 | G171: Topwear | H171: 0.057971014
A172: Winter Collection | B172: 20 | C172: 702 | D172: 0.028490028 | G172: Bottomwear | H172: 0.065527066
A173: Grand Total | B173: 218 | C173: 4491 | D173: 0.048541527 | G173: Grand Total | H173: 0.048541527

Sheet DASHBOARD
A1: 👗 FASHION & APPAREL RETAIL PERFORMANCE DASHBOARD | FY 2024 | India Market
